<annotation>
	<folder>train</folder>
	<filename>DJI Spark- Crossroads in Prague-0-01-08-152.jpg</filename>
	<path>C:\Users\Вадим\Desktop\train\DJI Spark- Crossroads in Prague-0-01-08-152.jpg</path>
	<source>
		<database>Unknown</database>
	</source>
	<size>
		<width>1280</width>
		<height>720</height>
		<depth>3</depth>
	</size>
	<segmented>0</segmented>
	<object>
		<name>car</name>
		<pose>Unspecified</pose>
		<truncated>0</truncated>
		<difficult>0</difficult>
		<bndbox>
			<xmin>270</xmin>
			<ymin>182</ymin>
			<xmax>312</xmax>
			<ymax>212</ymax>
		</bndbox>
	</object>
	<object>
		<name>car</name>
		<pose>Unspecified</pose>
		<truncated>0</truncated>
		<difficult>0</difficult>
		<bndbox>
			<xmin>478</xmin>
			<ymin>319</ymin>
			<xmax>523</xmax>
			<ymax>352</ymax>
		</bndbox>
	</object>
	<object>
		<name>car</name>
		<pose>Unspecified</pose>
		<truncated>0</truncated>
		<difficult>0</difficult>
		<bndbox>
			<xmin>439</xmin>
			<ymin>337</ymin>
			<xmax>476</xmax>
			<ymax>371</ymax>
		</bndbox>
	</object>
	<object>
		<name>car</name>
		<pose>Unspecified</pose>
		<truncated>0</truncated>
		<difficult>0</difficult>
		<bndbox>
			<xmin>663</xmin>
			<ymin>45</ymin>
			<xmax>692</xmax>
			<ymax>97</ymax>
		</bndbox>
	</object>
	<object>
		<name>car</name>
		<pose>Unspecified</pose>
		<truncated>1</truncated>
		<difficult>0</difficult>
		<bndbox>
			<xmin>652</xmin>
			<ymin>702</ymin>
			<xmax>674</xmax>
			<ymax>720</ymax>
		</bndbox>
	</object>
</annotation>
