<annotation verified="yes">
	<folder>DJI Spark- Crossroads in Prague (06.02.2019 18-25-06)</folder>
	<filename>DJI Spark- Crossroads in Prague 325.jpg</filename>
	<path>/home/fest/Загрузки/DJI Spark- Crossroads in Prague (06.02.2019 18-25-06)/DJI Spark- Crossroads in Prague 325.jpg</path>
	<source>
		<database>Unknown</database>
	</source>
	<size>
		<width>1280</width>
		<height>720</height>
		<depth>3</depth>
	</size>
	<segmented>0</segmented>
	<object>
		<name>car</name>
		<pose>Unspecified</pose>
		<truncated>0</truncated>
		<difficult>0</difficult>
		<bndbox>
			<xmin>481</xmin>
			<ymin>601</ymin>
			<xmax>507</xmax>
			<ymax>651</ymax>
		</bndbox>
	</object>
	<object>
		<name>car</name>
		<pose>Unspecified</pose>
		<truncated>0</truncated>
		<difficult>0</difficult>
		<bndbox>
			<xmin>508</xmin>
			<ymin>401</ymin>
			<xmax>544</xmax>
			<ymax>454</ymax>
		</bndbox>
	</object>
</annotation>
